<?xml version="1.0" encoding="iso-8859-15"?>
	<!DOCTYPE NIR SYSTEM 'nircompleto.dtd'>
	<NIR tipo="multivigente" xmlns="http://www.normeinrete.it/nir/2.2/" xmlns:dsp="http://www.normeinrete.it/nir/disposizioni/2.2/" xmlns:h="http://www.w3.org/HTML/1998/html4" xmlns:xlink="http://www.w3.org/1999/xlink">
		<DocumentoNIR nome="Circolare">
			<meta>
				<descrittori>
					<pubblicazione norm="" num="" tipo="" />
					<entratainvigore norm="20090713" />
					<redazione contributo="" id="red1" nome="Urp-Cnr" norm="" url="" />
					<urn finevigore="t2" iniziovigore="t1" valore="urn:nir:consiglio.nazionale.ricerche:circolare:2009-07-13;16" />
					<urn valore="urn:nir:consiglio.nazionale.ricerche:circolare:2009-07-13;51518" />
					<urn iniziovigore="t2" valore="urn:nir:consiglio.nazionale.ricerche:circolare:2009-07-13;16@2009-12-04" />
				</descrittori>
				<ciclodivita>
					<eventi>
						<evento data="20090713" fonte="ro1" id="t1" tipo="entrata in vigore" />
						<evento data="20091204" fonte="rp1" id="t2" tipo="modifica" />
					</eventi>
					<relazioni>
						<originale id="ro1" xlink:href="urn:nir:consiglio.nazionale.ricerche:circolare:2009-07-13;16" xlink:type="simple" />
						<passiva id="rp1" xlink:href="urn:nir:consiglio.nazionale.ricerche:circolare:2009-12-04;30" xlink:type="simple" />
					</relazioni>
				</ciclodivita>
				<proprietario xlink:type="simple">
					<cnr:meta xmlns:cnr="http://www.cnr.it/provvedimenti/2.2">
						<cnr:strutturaEmanante valore="Direzione Generale" />
						<cnr:autoritaEmanante valore="Direttore Generale" />
						<cnr:tipoDestinatario valore="Carattere generale" />
						<cnr:strutturaDestinataria valore="tutti" />
						<cnr:tipoProvvedimento />
						<cnr:dipartimento valore="carattere generale" />
					</cnr:meta>
				</proprietario>
				<disposizioni xlink:type="simple">
					<modifichepassive>
						<dsp:sostituzione completa="si" implicita="no">
							<dsp:pos xlink:href="#??" xlink:type="simple" />
							<dsp:norma xlink:href="urn:nir:consiglio.nazionale.ricerche:circolare:2009-12-04;30" xlink:type="simple">
								<dsp:pos xlink:href="urn:nir:consiglio.nazionale.ricerche:circolare:2009-12-04;30" xlink:type="simple" />
								<dsp:subarg>
									<ittig:notavigenza auto="circolare del Consiglio Nazionale delle Ricerche 4 dicembre 2009, n. 30" id="itt1" xmlns:ittig="http://www.ittig.cnr.it/provvedimenti/2.2" />
								</dsp:subarg>
							</dsp:norma>
							<dsp:novella>
								<dsp:pos xlink:href="#h2" xlink:type="simple" />
							</dsp:novella>
							<dsp:novellando>
								<dsp:pos xlink:href="#h1" xlink:type="simple" />
							</dsp:novellando>
						</dsp:sostituzione>
						<dsp:sostituzione completa="si" implicita="no">
							<dsp:pos xlink:href="#??" xlink:type="simple" />
							<dsp:norma xlink:href="urn:nir:consiglio.nazionale.ricerche:circolare:2009-12-04;30" xlink:type="simple">
								<dsp:pos xlink:href="urn:nir:consiglio.nazionale.ricerche:circolare:2009-12-04;30" xlink:type="simple" />
								<dsp:subarg>
									<ittig:notavigenza auto="circolare del Consiglio Nazionale delle Ricerche 4 dicembre 2009, n. 30" id="itt3" xmlns:ittig="http://www.ittig.cnr.it/provvedimenti/2.2" />
								</dsp:subarg>
							</dsp:norma>
							<dsp:novella>
								<dsp:pos xlink:href="#con6" xlink:type="simple" />
							</dsp:novella>
							<dsp:novellando>
								<dsp:pos xlink:href="#con5-t2" xlink:type="simple" />
							</dsp:novellando>
						</dsp:sostituzione>
					</modifichepassive>
				</disposizioni>
			</meta>
			<intestazione>
				<emanante>Consiglio Nazionale delle Ricerche</emanante>
				<tipoDoc>Circolare</tipoDoc>
				<dataDoc norm="20090713">13 luglio 2009</dataDoc>
				, n.
				<numDoc>16</numDoc>
				(AMMCNT - CNR n.
				<numDoc nome="protocollo">51518</numDoc>
				)
				<titoloDoc>
					Incarichi di collaborazione - Aggiornamenti derivanti dalla
					<rif xlink:href="urn:nir:stato:legge:2009;69" xlink:type="simple">Legge 69/2009</rif>
					e dal
					<rif xlink:href="urn:nir:stato:decreto.legge:2009;78" xlink:type="simple">D.L. 78/2009</rif>
					.
				</titoloDoc>
			</intestazione>
			<contenitore id="con1" nome="">
				<contenitore id="con2" nome="">
					<h:p>Ai</h:p>
					<h:p>Dirigenti/Direttori delle Unità Organiche e Strutture del CNR</h:p>
					<h:p>Collegio dei Revisori dei Conti</h:p>
					<h:p>LORO SEDI</h:p>
					<h:p />
				</contenitore>
				<contenitore id="con3" nome="">
					<h:p />
					<h:p>Negli ultimi giorni due testi di legge hanno apportato significative modifiche alla normativa relativa al conferimento di incarichi di collaborazione nella pubblica amministrazione.</h:p>
					<h:p />
					<h:p>
						In particolare l'
						<rif xlink:href="urn:nir:stato:legge:2009-06-18;69#art22-com2" xlink:type="simple">art. 22 comma 2 della legge 18 giugno 2009 n. 69</rif>
						e l'
						<mrif>
							art. 17
							<rif xlink:href="urn:nir:stato:decreto.legge:2009-07-01;78#art17-com27" xlink:type="simple">comma 27</rif>
							e
							<rif xlink:href="urn:nir:stato:decreto.legge:2009-07-01;78#art17-com30" xlink:type="simple">comma 30</rif>
							del Decreto legge 1 luglio 2009 n. 78
						</mrif>
						. Le novità di rilievo per i Centri di responsabilità del CNR sono illustrate nel dettaglio dalla Direttiva della Ragioneria della SAC (
						<rif xlink:href="#ann1" xlink:type="simple">All. 1</rif>
						).
					</h:p>
					<h:p />
					<h:p>Si raccomanda alle SS.LL. di prestare particolare attenzione alla corretta effettuazione del procedimento riguardante l'invio degli atti alla Corte dei Conti.</h:p>
				</contenitore>
			</contenitore>
			<formulafinale />
			<conclusione>
				<firma tipo="sottoscrizione">IL DIRETTORE GENERALE</firma>
			</conclusione>
			<annessi>
				<annesso id="ann1">
					<testata>
						<denAnnesso>Allegato 1</denAnnesso>
					</testata>
					<DocumentoNIR nome="xxxxx">
						<meta>
							<descrittori>
								<pubblicazione norm="" num="" tipo="GU" />
								<entratainvigore norm="" />
								<redazione id="red2" nome="" norm="" />
								<urn valore="urn:nir:consiglio.nazionale.ricerche:circolare:2009-07-13;16:allegato.1" />
							</descrittori>
							<proprietario xlink:type="simple">
								<cnr:meta xmlns:cnr="http://www.cnr.it/provvedimenti/2.2">
									<cnr:strutturaEmanante valore="Direzione Generale" />
									<cnr:autoritaEmanante valore="Direttore Generale" />
									<cnr:tipoDestinatario valore="Carattere generale" />
									<cnr:strutturaDestinataria valore="tutti" />
									<cnr:tipoProvvedimento valore="" />
									<cnr:dipartimento valore="carattere generale" />
								</cnr:meta>
							</proprietario>
						</meta>
						<intestazione>
							<emanante />
							<tipoDoc>Allegato alla Circolare</tipoDoc>
							<dataDoc norm="20090713">13 luglio 2009</dataDoc>
							, n.
							<numDoc>16</numDoc>
							(AMMCNT - CNR n.
							<numDoc nome="protocollo">51518</numDoc>
							)
							<titoloDoc>
								<h:span finevigore="t2" id="h1" iniziovigore="t1" status="abrogato">
									<rif xlink:href="pdf/c09-16a1.pdf" xlink:type="simple">Direttiva della Ragioneria della SAC n. Reg. RagSac 439/2009 del 10 luglio 2009</rif>
								</h:span>
								<h:span id="h2" iniziovigore="t2">
									<rif xlink:href="pdf/c09-30a2.pdf" xlink:type="simple">Direttiva della Ragioneria della SAC n. Reg. RagSac 679/2009 del 30 novembre 2009</rif>
								</h:span>
							</titoloDoc>
						</intestazione>
						<contenitore id="con4" nome="corpo">
							<contenitore finevigore="t2" id="con5-t2" iniziovigore="t1" nome="" status="abrogato">
								<h:p>e relativi allegati:</h:p>
								<h:ul>
									<h:li>
										All. 1
										<rif xlink:href="pdf/c09-16a1a1.pdf" xlink:type="simple">"Schema di "Contratto di prestazione d'opera in regime di collaborazione coordinata e continuativa"</rif>
										;
									</h:li>
									<h:li>
										All. 2
										<rif xlink:href="pdf/c09-16a1a2.pdf" xlink:type="simple">Schema di "Contratto di prestazione d'opera in regime di lavoro autonomo occasionale"</rif>
										;
									</h:li>
									<h:li>
										All. 3
										<rif xlink:href="pdf/c09-16a1a3.pdf" xlink:type="simple">Schema di "Collaborazione professionale di lavoro autonomo"</rif>
										;
									</h:li>
									<h:li>
										All. 4
										<rif xlink:href="pdf/c09-16a1a4.pdf" xlink:type="simple">Schema della nota di trasmissione degli atti alla Corte dei Conti</rif>
										;
									</h:li>
									<h:li>
										All. 5
										<rif xlink:href="pdf/c09-16a1a5.pdf" xlink:type="simple">Avviso interno di incarico</rif>
										;
									</h:li>
									<h:li>
										All. 6
										<rif xlink:href="pdf/c09-16a1a6.pdf" xlink:type="simple">Decisione a contrattare</rif>
										;
									</h:li>
									<h:li>
										All. 7
										<rif xlink:href="pdf/c09-16a1a7.pdf" xlink:type="simple">Avviso esterno di incarico</rif>
									</h:li>
								</h:ul>
							</contenitore>
							<contenitore id="con6" iniziovigore="t2" nome="">
								<h:p>
									[La Direttiva della Ragioneria della SAC n. Reg. RagSac 439/2009 del 10 luglio 2009 (e tutti gli allegati in essa contenuti) è sostituita dagli allegati alla
									<rif xlink:href="urn:nir:consiglio.nazionale.ricerche:circolare:2009;30" xlink:type="simple">circolare n. 30/2009</rif>
									.]
								</h:p>
							</contenitore>
						</contenitore>
					</DocumentoNIR>
				</annesso>
			</annessi>
		</DocumentoNIR>
	</NIR>
